{
    "ciudad": "Santa Rosa, Misiones",
    "fecha_actualizacion": "28/04/2026 04:46:38",
    "actual": {
        "temperatura": 11.3,
        "humedad": 81,
        "viento_velocidad": 9.0,
        "viento_direccion": 170,
        "lluvia": 0.0,
        "presion": 1000.2,
        "uv": 0.0
    },
    "historial": {
        "horas": [
            "2026-04-28T00:00",
            "2026-04-28T01:00",
            "2026-04-28T02:00",
            "2026-04-28T03:00",
            "2026-04-28T04:00",
            "2026-04-28T05:00",
            "2026-04-28T06:00",
            "2026-04-28T07:00",
            "2026-04-28T08:00",
            "2026-04-28T09:00",
            "2026-04-28T10:00",
            "2026-04-28T11:00",
            "2026-04-28T12:00",
            "2026-04-28T13:00",
            "2026-04-28T14:00",
            "2026-04-28T15:00",
            "2026-04-28T16:00",
            "2026-04-28T17:00",
            "2026-04-28T18:00",
            "2026-04-28T19:00",
            "2026-04-28T20:00",
            "2026-04-28T21:00",
            "2026-04-28T22:00",
            "2026-04-28T23:00"
        ],
        "temperatura": [
            11.6,
            11.2,
            10.8,
            10.6,
            10.6,
            10.4,
            10.2,
            11.2,
            13.4,
            15.1,
            16.7,
            18.0,
            19.0,
            19.6,
            19.9,
            19.4,
            18.5,
            16.9,
            16.5,
            15.6,
            14.9,
            14.5,
            14.6,
            14.3
        ],
        "humedad": [
            78,
            81,
            85,
            87,
            87,
            87,
            88,
            83,
            76,
            66,
            59,
            55,
            50,
            50,
            48,
            49,
            57,
            64,
            62,
            64,
            68,
            70,
            68,
            70
        ],
        "lluvia": [
            0.0,
            0.0,
            0.0,
            0.0,
            0.0,
            0.0,
            0.0,
            0.0,
            0.0,
            0.0,
            0.0,
            0.0,
            0.0,
            0.0,
            0.0,
            0.0,
            0.0,
            0.0,
            0.0,
            0.0,
            0.0,
            0.0,
            0.0,
            0.0
        ]
    }
}