{
    "ciudad": "Santa Rosa, Misiones",
    "fecha_actualizacion": "26/04/2026 03:53:42",
    "actual": {
        "temperatura": 21.1,
        "humedad": 98,
        "viento_velocidad": 6.9,
        "viento_direccion": 217,
        "lluvia": 0.0,
        "presion": 994.5,
        "uv": 0.0
    },
    "historial": {
        "horas": [
            "2026-04-25T00:00",
            "2026-04-25T01:00",
            "2026-04-25T02:00",
            "2026-04-25T03:00",
            "2026-04-25T04:00",
            "2026-04-25T05:00",
            "2026-04-25T06:00",
            "2026-04-25T07:00",
            "2026-04-25T08:00",
            "2026-04-25T09:00",
            "2026-04-25T10:00",
            "2026-04-25T11:00",
            "2026-04-25T12:00",
            "2026-04-25T13:00",
            "2026-04-25T14:00",
            "2026-04-25T15:00",
            "2026-04-25T16:00",
            "2026-04-25T17:00",
            "2026-04-25T18:00",
            "2026-04-25T19:00",
            "2026-04-25T20:00",
            "2026-04-25T21:00",
            "2026-04-25T22:00",
            "2026-04-25T23:00"
        ],
        "temperatura": [
            20.1,
            20.1,
            19.9,
            20.0,
            20.1,
            20.0,
            20.0,
            20.1,
            21.2,
            22.4,
            22.4,
            23.5,
            24.2,
            25.0,
            24.9,
            24.3,
            22.9,
            22.1,
            21.6,
            21.5,
            21.4,
            21.2,
            21.4,
            21.3
        ],
        "humedad": [
            98,
            96,
            98,
            98,
            98,
            99,
            99,
            99,
            95,
            86,
            90,
            84,
            80,
            79,
            78,
            79,
            94,
            96,
            98,
            98,
            97,
            98,
            98,
            98
        ],
        "lluvia": [
            0.0,
            0.0,
            0.1,
            0.5,
            0.9,
            0.3,
            0.8,
            0.5,
            0.2,
            0.2,
            0.4,
            0.3,
            0.1,
            0.0,
            0.0,
            0.0,
            0.6,
            0.4,
            0.6,
            0.2,
            0.0,
            0.0,
            0.0,
            0.0
        ]
    }
}